MANIFEST.in
README
pypi-overview.rst
rbtranslations.py
setup.cfg
setup.py
rbtranslations.egg-info/PKG-INFO
rbtranslations.egg-info/SOURCES.txt
rbtranslations.egg-info/dependency_links.txt
rbtranslations.egg-info/top_level.txt
tests/__init__.py
tests/test.properties
tests/test_de.properties
tests/test_de_AT.properties
tests/test_fr.properties
tests/trans-utf8.properties
tests/trans.properties
tests/translations.py