Metadata-Version: 1.0
Name: rbtranslations
Version: 0.9.3p3
Summary: Java ResourceBundle like approach to localization.
Home-page: http://packages.python.org/rbtranslations
Author: Michael N. Lipp
Author-email: mnl@mnl.de
License: MIT
Keywords: ResourceBundle Translations i18n l10n internationalization
Platform: any
Classifier: Development Status :: 4 - Beta
Classifier: Topic :: Software Development :: Internationalization
Classifier: License :: OSI Approved :: MIT License
